phonon_web_tools/__init__.py
phonon_web_tools/cli.py
phonon_web_tools/lattice.py
phonon_web_tools/phonon_web.py
phonon_web_tools/qe_phonon_tools.py
phonon_web_tools/utils.py
phonon_web_tools-0.1.5.dist-info/METADATA
phonon_web_tools-0.1.5.dist-info/WHEEL
phonon_web_tools-0.1.5.dist-info/entry_points.txt
phonon_web_tools-0.1.5.dist-info/RECORD
