Metadata-Version: 2.4
Name: phonon-web-tools
Version: 0.1.5
Summary: Tools to convert phonon visualization data into a web-friendly format.
Requires-Python: >=3.10
Requires-Dist: ase~=3.26
Requires-Dist: pymatgen
Requires-Dist: pyyaml
Requires-Dist: qe-tools~=2.3
Requires-Dist: seekpath>=1.0
